{
	"info": {
		"_postman_id": "04c0609f-2e93-4600-b1d6-1013a4618e8b",
		"name": "Veb servis aplikacije",
		"schema": "https://schema.getpostman.com/json/collection/v2.1.0/collection.json"
	},
	"item": [
		{
			"name": "Administrator",
			"item": [
				{
					"name": "Get all administrators",
					"request": {
						"method": "GET",
						"header": [],
						"url": {
							"raw": "http://localhost:3000/api/administrator/",
							"protocol": "http",
							"host": [
								"localhost"
							],
							"port": "3000",
							"path": [
								"api",
								"administrator",
								""
							]
						}
					},
					"response": [
						{
							"name": "Get all administrators",
							"originalRequest": {
								"method": "GET",
								"header": [],
								"url": {
									"raw": "http://localhost:3000/api/administrator/",
									"protocol": "http",
									"host": [
										"localhost"
									],
									"port": "3000",
									"path": [
										"api",
										"administrator",
										""
									]
								}
							},
							"status": "OK",
							"code": 200,
							"_postman_previewlanguage": "json",
							"header": [
								{
									"key": "X-Powered-By",
									"value": "Express"
								},
								{
									"key": "Content-Type",
									"value": "application/json; charset=utf-8"
								},
								{
									"key": "Content-Length",
									"value": "138"
								},
								{
									"key": "ETag",
									"value": "W/\"8a-6yGFSIsWtxmEau8dcZcjPx97+gI\""
								},
								{
									"key": "Date",
									"value": "Sun, 10 Jan 2021 22:09:02 GMT"
								},
								{
									"key": "Connection",
									"value": "keep-alive"
								}
							],
							"cookie": [],
							"body": "[\n    {\n        \"administratorId\": 1,\n        \"username\": \"vanja\",\n        \"passwordHash\": \"vanjanina11\"\n    },\n    {\n        \"administratorId\": 2,\n        \"username\": \"aleksa\",\n        \"passwordHash\": \"aleksej\"\n    }\n]"
						}
					]
				},
				{
					"name": "Get a single administrator",
					"request": {
						"method": "GET",
						"header": [],
						"url": {
							"raw": "http://localhost:3000/api/administrator/1",
							"protocol": "http",
							"host": [
								"localhost"
							],
							"port": "3000",
							"path": [
								"api",
								"administrator",
								"1"
							]
						}
					},
					"response": [
						{
							"name": "Get a single administrator",
							"originalRequest": {
								"method": "GET",
								"header": [],
								"url": {
									"raw": "http://localhost:3000/api/administrator/1",
									"protocol": "http",
									"host": [
										"localhost"
									],
									"port": "3000",
									"path": [
										"api",
										"administrator",
										"1"
									]
								}
							},
							"status": "OK",
							"code": 200,
							"_postman_previewlanguage": "json",
							"header": [
								{
									"key": "X-Powered-By",
									"value": "Express"
								},
								{
									"key": "Content-Type",
									"value": "application/json; charset=utf-8"
								},
								{
									"key": "Content-Length",
									"value": "69"
								},
								{
									"key": "ETag",
									"value": "W/\"45-M6qyHz70TEYnFEDatnESEHMdb1o\""
								},
								{
									"key": "Date",
									"value": "Sun, 10 Jan 2021 22:11:16 GMT"
								},
								{
									"key": "Connection",
									"value": "keep-alive"
								}
							],
							"cookie": [],
							"body": "{\n    \"administratorId\": 1,\n    \"username\": \"vanja\",\n    \"passwordHash\": \"vanjanina11\"\n}"
						}
					]
				},
				{
					"name": "Add a new administrator",
					"request": {
						"method": "POST",
						"header": [
							{
								"key": "Content-Type",
								"value": "application/json",
								"type": "text"
							}
						],
						"body": {
							"mode": "raw",
							"raw": "{\n    \"username\": \"vsmiljkovic\",\n    \"password\": \"vanjicaboss\"\n}"
						},
						"url": {
							"raw": "http://localhost:3000/api/administrator/",
							"protocol": "http",
							"host": [
								"localhost"
							],
							"port": "3000",
							"path": [
								"api",
								"administrator",
								""
							]
						}
					},
					"response": []
				},
				{
					"name": "Edit an existing administrator",
					"request": {
						"method": "PATCH",
						"header": [
							{
								"key": "Content-Type",
								"value": "application/json",
								"type": "text"
							}
						],
						"body": {
							"mode": "raw",
							"raw": "{\n    \"password\" : \"NekaNovalozinka!\"\n}"
						},
						"url": {
							"raw": "http://localhost:3000/api/administrator/1/",
							"protocol": "http",
							"host": [
								"localhost"
							],
							"port": "3000",
							"path": [
								"api",
								"administrator",
								"1",
								""
							]
						}
					},
					"response": []
				},
				{
					"name": "Edit a non-existing administrator",
					"request": {
						"method": "PATCH",
						"header": [
							{
								"key": "Content-Type",
								"value": "application/json",
								"type": "text"
							}
						],
						"body": {
							"mode": "raw",
							"raw": "{\n    \"password\": \"NOVIPASS\"\n}"
						},
						"url": {
							"raw": "http://localhost:3000/api/administrator/67/",
							"protocol": "http",
							"host": [
								"localhost"
							],
							"port": "3000",
							"path": [
								"api",
								"administrator",
								"67",
								""
							]
						}
					},
					"response": [
						{
							"name": "Edit a non-existing administrator",
							"originalRequest": {
								"method": "POST",
								"header": [
									{
										"key": "Content-Type",
										"value": "application/json",
										"type": "text"
									}
								],
								"body": {
									"mode": "raw",
									"raw": "{\n    \"password\": \"NOVIPASS\"\n}"
								},
								"url": {
									"raw": "http://localhost:3000/api/administrator/67/",
									"protocol": "http",
									"host": [
										"localhost"
									],
									"port": "3000",
									"path": [
										"api",
										"administrator",
										"67",
										""
									]
								}
							},
							"status": "Created",
							"code": 201,
							"_postman_previewlanguage": "json",
							"header": [
								{
									"key": "X-Powered-By",
									"value": "Express"
								},
								{
									"key": "Content-Type",
									"value": "application/json; charset=utf-8"
								},
								{
									"key": "Content-Length",
									"value": "52"
								},
								{
									"key": "ETag",
									"value": "W/\"34-TohoSz0THfgyH4V7rCdfcfXcq54\""
								},
								{
									"key": "Date",
									"value": "Sun, 10 Jan 2021 22:59:33 GMT"
								},
								{
									"key": "Connection",
									"value": "keep-alive"
								}
							],
							"cookie": [],
							"body": "{\n    \"status\": \"error\",\n    \"statusCode\": -1002,\n    \"message\": null\n}"
						}
					]
				},
				{
					"name": "Get a single non-existing administrator",
					"request": {
						"method": "GET",
						"header": [],
						"url": {
							"raw": "http://localhost:3000/api/administrator/67/",
							"protocol": "http",
							"host": [
								"localhost"
							],
							"port": "3000",
							"path": [
								"api",
								"administrator",
								"67",
								""
							]
						}
					},
					"response": [
						{
							"name": "Get a single non-existing administrator",
							"originalRequest": {
								"method": "GET",
								"header": [],
								"url": {
									"raw": "http://localhost:3000/api/administrator/67/",
									"protocol": "http",
									"host": [
										"localhost"
									],
									"port": "3000",
									"path": [
										"api",
										"administrator",
										"67",
										""
									]
								}
							},
							"status": "OK",
							"code": 200,
							"_postman_previewlanguage": "json",
							"header": [
								{
									"key": "X-Powered-By",
									"value": "Express"
								},
								{
									"key": "Content-Type",
									"value": "application/json; charset=utf-8"
								},
								{
									"key": "Content-Length",
									"value": "52"
								},
								{
									"key": "ETag",
									"value": "W/\"34-TohoSz0THfgyH4V7rCdfcfXcq54\""
								},
								{
									"key": "Date",
									"value": "Sun, 10 Jan 2021 23:04:19 GMT"
								},
								{
									"key": "Connection",
									"value": "keep-alive"
								}
							],
							"cookie": [],
							"body": "{\n    \"status\": \"error\",\n    \"statusCode\": -1002,\n    \"message\": null\n}"
						}
					]
				}
			],
			"event": [
				{
					"listen": "prerequest",
					"script": {
						"type": "text/javascript",
						"exec": [
							""
						]
					}
				},
				{
					"listen": "test",
					"script": {
						"type": "text/javascript",
						"exec": [
							""
						]
					}
				}
			]
		},
		{
			"name": "Article",
			"item": [
				{
					"name": "POSTcreateFull",
					"request": {
						"method": "POST",
						"header": [
							{
								"key": "Content-Type",
								"value": "application/json",
								"type": "text"
							}
						],
						"body": {
							"mode": "raw",
							"raw": "{\n    \"name\": \"ACME HD11 1TB\",\n    \"categoryId\": 5,\n    \"excerpt\": \"Neki kratak opis\",\n    \"description\": \"Detaljan opis\",\n    \"price\": 56.89,\n    \"features\": [\n        {\n            \"featureId\": 1,\n            \"value\": \"1TB\"\n        },\n        {\n            \"featureId\": 3,\n            \"value\": \"SSD\"\n        }\n    ]\n}"
						},
						"url": {
							"raw": "http://localhost:3000/api/article/createFull/",
							"protocol": "http",
							"host": [
								"localhost"
							],
							"port": "3000",
							"path": [
								"api",
								"article",
								"createFull",
								""
							]
						}
					},
					"response": []
				},
				{
					"name": "Upload article photo",
					"request": {
						"method": "POST",
						"header": [],
						"body": {
							"mode": "formdata",
							"formdata": [
								{
									"key": "photo",
									"type": "file",
									"src": "/Users/vanja/Desktop/profil.jpg"
								}
							]
						},
						"url": {
							"raw": "http://localhost:3000/api/article/1/uploadPhoto/",
							"protocol": "http",
							"host": [
								"localhost"
							],
							"port": "3000",
							"path": [
								"api",
								"article",
								"1",
								"uploadPhoto",
								""
							]
						}
					},
					"response": [
						{
							"name": "Upload article photo - success",
							"originalRequest": {
								"method": "POST",
								"header": [],
								"body": {
									"mode": "formdata",
									"formdata": [
										{
											"key": "photo",
											"type": "file",
											"src": "/Users/vanja/Desktop/profil.jpg"
										}
									]
								},
								"url": {
									"raw": "http://localhost:3000/api/article/2/uploadPhoto/",
									"protocol": "http",
									"host": [
										"localhost"
									],
									"port": "3000",
									"path": [
										"api",
										"article",
										"2",
										"uploadPhoto",
										""
									]
								}
							},
							"status": "Created",
							"code": 201,
							"_postman_previewlanguage": "json",
							"header": [
								{
									"key": "X-Powered-By",
									"value": "Express"
								},
								{
									"key": "Content-Type",
									"value": "application/json; charset=utf-8"
								},
								{
									"key": "Content-Length",
									"value": "73"
								},
								{
									"key": "ETag",
									"value": "W/\"49-ctGuX5O0+7jEY86ItkqBAloWGas\""
								},
								{
									"key": "Date",
									"value": "Tue, 12 Jan 2021 21:14:34 GMT"
								},
								{
									"key": "Connection",
									"value": "keep-alive"
								}
							],
							"cookie": [],
							"body": "{\n    \"articleId\": \"2\",\n    \"imagePath\": \"2021112-5811116908-profil.jpg\",\n    \"photoId\": 3\n}"
						},
						{
							"name": "Upload article photo - bad file extension",
							"originalRequest": {
								"method": "POST",
								"header": [],
								"body": {
									"mode": "formdata",
									"formdata": [
										{
											"key": "photo",
											"type": "file",
											"src": "/Users/vanja/Desktop/proba.py"
										}
									]
								},
								"url": {
									"raw": "http://localhost:3000/api/article/2/uploadPhoto/",
									"protocol": "http",
									"host": [
										"localhost"
									],
									"port": "3000",
									"path": [
										"api",
										"article",
										"2",
										"uploadPhoto",
										""
									]
								}
							},
							"status": "Created",
							"code": 201,
							"_postman_previewlanguage": "json",
							"header": [
								{
									"key": "X-Powered-By",
									"value": "Express"
								},
								{
									"key": "Content-Type",
									"value": "application/json; charset=utf-8"
								},
								{
									"key": "Content-Length",
									"value": "69"
								},
								{
									"key": "ETag",
									"value": "W/\"45-/1BctOZfI9HUiikyGHz7sO4T6hY\""
								},
								{
									"key": "Date",
									"value": "Wed, 13 Jan 2021 10:56:41 GMT"
								},
								{
									"key": "Connection",
									"value": "keep-alive"
								}
							],
							"cookie": [],
							"body": "{\n    \"status\": \"error\",\n    \"statusCode\": -4002,\n    \"message\": \"Bad file extension!\"\n}"
						}
					]
				},
				{
					"name": "Get a single article",
					"request": {
						"method": "GET",
						"header": [],
						"url": {
							"raw": "http://localhost:3000/api/article/2/",
							"protocol": "http",
							"host": [
								"localhost"
							],
							"port": "3000",
							"path": [
								"api",
								"article",
								"2",
								""
							]
						}
					},
					"response": [
						{
							"name": "Get a single article",
							"originalRequest": {
								"method": "GET",
								"header": [],
								"url": {
									"raw": "http://localhost:3000/api/article/2/",
									"protocol": "http",
									"host": [
										"localhost"
									],
									"port": "3000",
									"path": [
										"api",
										"article",
										"2",
										""
									]
								}
							},
							"status": "OK",
							"code": 200,
							"_postman_previewlanguage": "json",
							"header": [
								{
									"key": "X-Powered-By",
									"value": "Express"
								},
								{
									"key": "Content-Type",
									"value": "application/json; charset=utf-8"
								},
								{
									"key": "Content-Length",
									"value": "774"
								},
								{
									"key": "ETag",
									"value": "W/\"306-M5EXyiYSR0r0/41m5lMSdBMUn6k\""
								},
								{
									"key": "Date",
									"value": "Thu, 14 Jan 2021 13:16:35 GMT"
								},
								{
									"key": "Connection",
									"value": "keep-alive"
								}
							],
							"cookie": [],
							"body": "{\n    \"articleId\": 2,\n    \"name\": \"ACME HD11 1TB\",\n    \"categoryId\": 5,\n    \"excerpt\": \"Neki kratak opis\",\n    \"description\": \"Detaljan opis\",\n    \"status\": \"available\",\n    \"isPromoted\": 0,\n    \"createdAt\": \"2021-01-12T12:27:19.000Z\",\n    \"category\": {\n        \"categoryId\": 5,\n        \"name\": \"Hard diskovi\",\n        \"imagePath\": \"assets/pc/memory/hard.jpg\",\n        \"parentCategoryId\": 4\n    },\n    \"photos\": [\n        {\n            \"photoId\": 3,\n            \"articleId\": 2,\n            \"imagePath\": \"2021112-5811116908-profil.jpg\"\n        }\n    ],\n    \"articlePrices\": [\n        {\n            \"articlePriceId\": 4,\n            \"articleId\": 2,\n            \"price\": \"56.89\",\n            \"createdAt\": \"2021-01-12T12:27:19.000Z\"\n        }\n    ],\n    \"documentations\": [],\n    \"articleFeatures\": [\n        {\n            \"articleFeatureId\": 4,\n            \"articleId\": 2,\n            \"featureId\": 1,\n            \"value\": \"1TB\"\n        },\n        {\n            \"articleFeatureId\": 5,\n            \"articleId\": 2,\n            \"featureId\": 3,\n            \"value\": \"SSD\"\n        }\n    ],\n    \"features\": [\n        {\n            \"featureId\": 1,\n            \"name\": \"Kapacitet\",\n            \"categoryId\": 5\n        },\n        {\n            \"featureId\": 3,\n            \"name\": \"Tehnologija\",\n            \"categoryId\": 5\n        }\n    ]\n}"
						}
					]
				},
				{
					"name": "Delete a single  article photo",
					"request": {
						"method": "DELETE",
						"header": [],
						"url": {
							"raw": "http://localhost:3000/api/article/1/deletePhoto/4/",
							"protocol": "http",
							"host": [
								"localhost"
							],
							"port": "3000",
							"path": [
								"api",
								"article",
								"1",
								"deletePhoto",
								"4",
								""
							]
						}
					},
					"response": []
				},
				{
					"name": "Edit a single article without editing a features",
					"request": {
						"method": "PATCH",
						"header": [],
						"body": {
							"mode": "raw",
							"raw": "{\n    \"name\": \"ACME HDI1 1024GB\",\n    \"categoryId\": 5,\n    \"excerpt\": \"Kratak opis 2\",\n    \"description\": \"Duzi opis 2\",\n    \"status\": \"visible\",\n    \"isPromoted\": 1,\n    \"price\": 57.11,\n    \"features\": null\n}",
							"options": {
								"raw": {
									"language": "json"
								}
							}
						},
						"url": {
							"raw": "http://localhost:3000/api/article/2/",
							"protocol": "http",
							"host": [
								"localhost"
							],
							"port": "3000",
							"path": [
								"api",
								"article",
								"2",
								""
							]
						}
					},
					"response": [
						{
							"name": "Edit a single article without editing a features",
							"originalRequest": {
								"method": "PATCH",
								"header": [],
								"body": {
									"mode": "raw",
									"raw": "{\n    \"name\": \"ACME HDI1 1024GB\",\n    \"categoryId\": 5,\n    \"excerpt\": \"Kratak opis 2\",\n    \"description\": \"Duzi opis 2\",\n    \"status\": \"visible\",\n    \"isPromoted\": 1,\n    \"price\": 57.11,\n    \"features\": null\n}",
									"options": {
										"raw": {
											"language": "json"
										}
									}
								},
								"url": {
									"raw": "http://localhost:3000/api/article/2/",
									"protocol": "http",
									"host": [
										"localhost"
									],
									"port": "3000",
									"path": [
										"api",
										"article",
										"2",
										""
									]
								}
							},
							"status": "OK",
							"code": 200,
							"_postman_previewlanguage": "json",
							"header": [
								{
									"key": "X-Powered-By",
									"value": "Express"
								},
								{
									"key": "Content-Type",
									"value": "application/json; charset=utf-8"
								},
								{
									"key": "Content-Length",
									"value": "757"
								},
								{
									"key": "ETag",
									"value": "W/\"2f5-zTJwjLbGBLJ/ap5ttrM+V89wgoU\""
								},
								{
									"key": "Date",
									"value": "Thu, 14 Jan 2021 17:21:37 GMT"
								},
								{
									"key": "Connection",
									"value": "keep-alive"
								}
							],
							"cookie": [],
							"body": "{\n    \"articleId\": 2,\n    \"name\": \"ACME HDI1 1024GB\",\n    \"categoryId\": 5,\n    \"excerpt\": \"Kratak opis 2\",\n    \"description\": \"Duzi opis 2\",\n    \"status\": \"visible\",\n    \"isPromoted\": 1,\n    \"createdAt\": \"2021-01-12T12:27:19.000Z\",\n    \"category\": {\n        \"categoryId\": 5,\n        \"name\": \"Hard diskovi\",\n        \"imagePath\": \"assets/pc/memory/hard.jpg\",\n        \"parentCategoryId\": 4\n    },\n    \"articleFeatures\": [\n        {\n            \"articleFeatureId\": 4,\n            \"articleId\": 2,\n            \"featureId\": 1,\n            \"value\": \"1TB\"\n        },\n        {\n            \"articleFeatureId\": 5,\n            \"articleId\": 2,\n            \"featureId\": 3,\n            \"value\": \"SSD\"\n        }\n    ],\n    \"features\": [\n        {\n            \"featureId\": 1,\n            \"name\": \"Kapacitet\",\n            \"categoryId\": 5\n        },\n        {\n            \"featureId\": 3,\n            \"name\": \"Tehnologija\",\n            \"categoryId\": 5\n        }\n    ],\n    \"articlePrices\": [\n        {\n            \"articlePriceId\": 4,\n            \"articleId\": 2,\n            \"price\": \"56.89\",\n            \"createdAt\": \"2021-01-12T12:27:19.000Z\"\n        },\n        {\n            \"articlePriceId\": 5,\n            \"articleId\": 2,\n            \"price\": \"57.11\",\n            \"createdAt\": \"2021-01-14T17:21:37.000Z\"\n        }\n    ]\n}"
						}
					]
				},
				{
					"name": "Edit a single article with editing a features Copy",
					"request": {
						"method": "PATCH",
						"header": [],
						"body": {
							"mode": "raw",
							"raw": "{\n    \"name\": \"ACME HDI1 1024GB\",\n    \"categoryId\": 5,\n    \"excerpt\": \"Kratak opis 2\",\n    \"description\": \"Duzi opis 2\",\n    \"status\": \"visible\",\n    \"isPromoted\": 1,\n    \"price\": 57.11,\n    \"features\": [\n        {\n            \"featureId\": 1,\n            \"value\": \"1024GB\"\n        }, \n        {\n            \"featureId\": 2,\n            \"value\": \"SATA 3.0\"\n        }\n    ]\n}",
							"options": {
								"raw": {
									"language": "json"
								}
							}
						},
						"url": {
							"raw": "http://localhost:3000/api/article/2/",
							"protocol": "http",
							"host": [
								"localhost"
							],
							"port": "3000",
							"path": [
								"api",
								"article",
								"2",
								""
							]
						}
					},
					"response": [
						{
							"name": "Edit a single article with editing a features Copy",
							"originalRequest": {
								"method": "PATCH",
								"header": [],
								"body": {
									"mode": "raw",
									"raw": "{\n    \"name\": \"ACME HDI1 1024GB\",\n    \"categoryId\": 5,\n    \"excerpt\": \"Kratak opis 2\",\n    \"description\": \"Duzi opis 2\",\n    \"status\": \"visible\",\n    \"isPromoted\": 1,\n    \"price\": 57.11,\n    \"features\": [\n        {\n            \"featureId\": 1,\n            \"value\": \"1024GB\"\n        }, \n        {\n            \"featureId\": 2,\n            \"value\": \"SATA 3.0\"\n        }\n    ]\n}",
									"options": {
										"raw": {
											"language": "json"
										}
									}
								},
								"url": {
									"raw": "http://localhost:3000/api/article/2/",
									"protocol": "http",
									"host": [
										"localhost"
									],
									"port": "3000",
									"path": [
										"api",
										"article",
										"2",
										""
									]
								}
							},
							"status": "OK",
							"code": 200,
							"_postman_previewlanguage": "json",
							"header": [
								{
									"key": "X-Powered-By",
									"value": "Express"
								},
								{
									"key": "Content-Type",
									"value": "application/json; charset=utf-8"
								},
								{
									"key": "Content-Length",
									"value": "757"
								},
								{
									"key": "ETag",
									"value": "W/\"2f5-Ro/GNtZGjNSbA6AMIJZ8LX6bVmY\""
								},
								{
									"key": "Date",
									"value": "Thu, 14 Jan 2021 17:33:02 GMT"
								},
								{
									"key": "Connection",
									"value": "keep-alive"
								}
							],
							"cookie": [],
							"body": "{\n    \"articleId\": 2,\n    \"name\": \"ACME HDI1 1024GB\",\n    \"categoryId\": 5,\n    \"excerpt\": \"Kratak opis 2\",\n    \"description\": \"Duzi opis 2\",\n    \"status\": \"visible\",\n    \"isPromoted\": 1,\n    \"createdAt\": \"2021-01-12T12:27:19.000Z\",\n    \"category\": {\n        \"categoryId\": 5,\n        \"name\": \"Hard diskovi\",\n        \"imagePath\": \"assets/pc/memory/hard.jpg\",\n        \"parentCategoryId\": 4\n    },\n    \"articleFeatures\": [\n        {\n            \"articleFeatureId\": 6,\n            \"articleId\": 2,\n            \"featureId\": 1,\n            \"value\": \"1024GB\"\n        },\n        {\n            \"articleFeatureId\": 7,\n            \"articleId\": 2,\n            \"featureId\": 2,\n            \"value\": \"SATA 3.0\"\n        }\n    ],\n    \"features\": [\n        {\n            \"featureId\": 1,\n            \"name\": \"Kapacitet\",\n            \"categoryId\": 5\n        },\n        {\n            \"featureId\": 2,\n            \"name\": \"Tip\",\n            \"categoryId\": 5\n        }\n    ],\n    \"articlePrices\": [\n        {\n            \"articlePriceId\": 4,\n            \"articleId\": 2,\n            \"price\": \"56.89\",\n            \"createdAt\": \"2021-01-12T12:27:19.000Z\"\n        },\n        {\n            \"articlePriceId\": 5,\n            \"articleId\": 2,\n            \"price\": \"57.11\",\n            \"createdAt\": \"2021-01-14T17:21:37.000Z\"\n        }\n    ]\n}"
						}
					]
				}
			],
			"event": [
				{
					"listen": "prerequest",
					"script": {
						"type": "text/javascript",
						"exec": [
							""
						]
					}
				},
				{
					"listen": "test",
					"script": {
						"type": "text/javascript",
						"exec": [
							""
						]
					}
				}
			]
		},
		{
			"name": "Auth",
			"item": [
				{
					"name": "Administrator Login",
					"request": {
						"method": "POST",
						"header": [
							{
								"key": "Content-Type",
								"type": "text",
								"value": "application/json"
							}
						],
						"body": {
							"mode": "raw",
							"raw": "{\n    \"username\" : \"admin\",\n    \"password\" : \"admin\"\n}"
						},
						"url": {
							"raw": "http://localhost:3000/auth/administrator/login",
							"protocol": "http",
							"host": [
								"localhost"
							],
							"port": "3000",
							"path": [
								"auth",
								"administrator",
								"login"
							]
						}
					},
					"response": [
						{
							"name": "Login - when the administrator exists but the username is not correct",
							"originalRequest": {
								"method": "POST",
								"header": [
									{
										"key": "Content-Type",
										"value": "application/json",
										"type": "text"
									}
								],
								"body": {
									"mode": "raw",
									"raw": "{\n    \"username\" : \"admin1\",\n    \"password\" : \"admin\"\n}"
								},
								"url": {
									"raw": "http://localhost:3000/auth/login",
									"protocol": "http",
									"host": [
										"localhost"
									],
									"port": "3000",
									"path": [
										"auth",
										"login"
									]
								}
							},
							"status": "Created",
							"code": 201,
							"_postman_previewlanguage": "json",
							"header": [
								{
									"key": "X-Powered-By",
									"value": "Express"
								},
								{
									"key": "Content-Type",
									"value": "application/json; charset=utf-8"
								},
								{
									"key": "Content-Length",
									"value": "52"
								},
								{
									"key": "ETag",
									"value": "W/\"34-jVzHjGg0W81AgoBNOOnaoLkouLY\""
								},
								{
									"key": "Date",
									"value": "Tue, 12 Jan 2021 17:30:56 GMT"
								},
								{
									"key": "Connection",
									"value": "keep-alive"
								}
							],
							"cookie": [],
							"body": "{\n    \"status\": \"error\",\n    \"statusCode\": -3001,\n    \"message\": null\n}"
						},
						{
							"name": "Login - when administrator exists and pass is correct",
							"originalRequest": {
								"method": "POST",
								"header": [
									{
										"key": "Content-Type",
										"value": "application/json",
										"type": "text"
									}
								],
								"body": {
									"mode": "raw",
									"raw": "{\n    \"username\" : \"admin\",\n    \"password\" : \"admin\"\n}"
								},
								"url": {
									"raw": "http://localhost:3000/auth/login",
									"protocol": "http",
									"host": [
										"localhost"
									],
									"port": "3000",
									"path": [
										"auth",
										"login"
									]
								}
							},
							"status": "Created",
							"code": 201,
							"_postman_previewlanguage": "json",
							"header": [
								{
									"key": "X-Powered-By",
									"value": "Express"
								},
								{
									"key": "Content-Type",
									"value": "application/json; charset=utf-8"
								},
								{
									"key": "Content-Length",
									"value": "290"
								},
								{
									"key": "ETag",
									"value": "W/\"122-hzponB03XVqHiv3MSfSPPRkyrDU\""
								},
								{
									"key": "Date",
									"value": "Tue, 12 Jan 2021 17:28:20 GMT"
								},
								{
									"key": "Connection",
									"value": "keep-alive"
								}
							],
							"cookie": [],
							"body": "{\n    \"administratorId\": 4,\n    \"username\": \"admin\",\n    \"token\": \"eyJhbGciOiJIUzI1NiIsInR5cCI6IkpXVCJ9.eyJhZG1pbmlzdHJhdG9ySWQiOjQsInVzZXJuYW1lIjoiYWRtaW4iLCJleHAiOjE2MTE2ODIxMDAuNTM3LCJpcCI6Ijo6MSIsInVhIjoiUG9zdG1hblJ1bnRpbWUvNy4yNi44IiwiaWF0IjoxNjEwNDcyNTAwfQ.VTizrPu1EFEeDu1VXk4rqzCMpkV2GpcHhsE9CKy-foY\"\n}"
						},
						{
							"name": "Login - when the administrator exists but the password is not correct",
							"originalRequest": {
								"method": "POST",
								"header": [
									{
										"key": "Content-Type",
										"value": "application/json",
										"type": "text"
									}
								],
								"body": {
									"mode": "raw",
									"raw": "{\n    \"username\" : \"admin\",\n    \"password\" : \"admin1\"\n}"
								},
								"url": {
									"raw": "http://localhost:3000/auth/login",
									"protocol": "http",
									"host": [
										"localhost"
									],
									"port": "3000",
									"path": [
										"auth",
										"login"
									]
								}
							},
							"status": "Created",
							"code": 201,
							"_postman_previewlanguage": "json",
							"header": [
								{
									"key": "X-Powered-By",
									"value": "Express"
								},
								{
									"key": "Content-Type",
									"value": "application/json; charset=utf-8"
								},
								{
									"key": "Content-Length",
									"value": "52"
								},
								{
									"key": "ETag",
									"value": "W/\"34-yGnd1fUn+KRemOJUJKfIJoExxS4\""
								},
								{
									"key": "Date",
									"value": "Tue, 12 Jan 2021 17:31:42 GMT"
								},
								{
									"key": "Connection",
									"value": "keep-alive"
								}
							],
							"cookie": [],
							"body": "{\n    \"status\": \"error\",\n    \"statusCode\": -3002,\n    \"message\": null\n}"
						}
					]
				},
				{
					"name": "User Login",
					"request": {
						"method": "POST",
						"header": [
							{
								"key": "Content-Type",
								"type": "text",
								"value": "application/json"
							}
						],
						"body": {
							"mode": "raw",
							"raw": "{\n    \"email\" : \"test@test.com\",\n    \"password\" : \"abc\"\n}"
						},
						"url": {
							"raw": "http://localhost:3000/auth/user/login",
							"protocol": "http",
							"host": [
								"localhost"
							],
							"port": "3000",
							"path": [
								"auth",
								"user",
								"login"
							]
						}
					},
					"response": [
						{
							"name": "User Login",
							"originalRequest": {
								"method": "POST",
								"header": [
									{
										"key": "Content-Type",
										"type": "text",
										"value": "application/json"
									}
								],
								"body": {
									"mode": "raw",
									"raw": "{\n    \"email\" : \"test@test.com\",\n    \"password\" : \"abc\"\n}"
								},
								"url": {
									"raw": "http://localhost:3000/auth/user/login",
									"protocol": "http",
									"host": [
										"localhost"
									],
									"port": "3000",
									"path": [
										"auth",
										"user",
										"login"
									]
								}
							},
							"status": "Created",
							"code": 201,
							"_postman_previewlanguage": "json",
							"header": [
								{
									"key": "X-Powered-By",
									"value": "Express"
								},
								{
									"key": "Content-Type",
									"value": "application/json; charset=utf-8"
								},
								{
									"key": "Content-Length",
									"value": "314"
								},
								{
									"key": "ETag",
									"value": "W/\"13a-WQiXoN8jZRPnycjlBddQ6uYR2Gk\""
								},
								{
									"key": "Date",
									"value": "Thu, 14 Jan 2021 20:00:38 GMT"
								},
								{
									"key": "Connection",
									"value": "keep-alive"
								}
							],
							"cookie": [],
							"body": "{\n    \"id\": 1,\n    \"identity\": \"test@test.com\",\n    \"token\": \"eyJhbGciOiJIUzI1NiIsInR5cCI6IkpXVCJ9.eyJyb2xlIjoidXNlciIsImFkbWluaXN0cmF0b3JJZCI6MSwiaWRlbnRpdHkiOiJ0ZXN0QHRlc3QuY29tIiwiZXhwIjoxNjExODY0MDM4LjkzNSwiaXAiOiI6OjEiLCJ1YSI6IlBvc3RtYW5SdW50aW1lLzcuMjYuOCIsImlhdCI6MTYxMDY1NDQzOH0.2YhGkHC3j8NI8pYfVJFUwv4gUBiMLS9fulqBuGDO_X4\"\n}"
						}
					]
				},
				{
					"name": "Register a new user account",
					"request": {
						"method": "POST",
						"header": [],
						"body": {
							"mode": "raw",
							"raw": "{\n    \"email\": \"test@test.com\",\n    \"password\": \"abc\",\n    \"forename\": \"Neko\",\n    \"surname\": \"Vanjic\",\n    \"phoneNumber\": \"+381657788965\",\n    \"postalAddress\": \"Put za negde bb, Beograd, Srbija\"\n}",
							"options": {
								"raw": {
									"language": "json"
								}
							}
						},
						"url": {
							"raw": "http://localhost:3000/auth/user/register",
							"protocol": "http",
							"host": [
								"localhost"
							],
							"port": "3000",
							"path": [
								"auth",
								"user",
								"register"
							]
						}
					},
					"response": []
				}
			],
			"auth": {
				"type": "noauth"
			},
			"event": [
				{
					"listen": "prerequest",
					"script": {
						"type": "text/javascript",
						"exec": [
							""
						]
					}
				},
				{
					"listen": "test",
					"script": {
						"type": "text/javascript",
						"exec": [
							""
						]
					}
				}
			]
		},
		{
			"name": "Feature",
			"item": [
				{
					"name": "Get all features",
					"request": {
						"method": "GET",
						"header": [],
						"url": {
							"raw": "http://localhost:3000/api/feature/",
							"protocol": "http",
							"host": [
								"localhost"
							],
							"port": "3000",
							"path": [
								"api",
								"feature",
								""
							]
						}
					},
					"response": [
						{
							"name": "Get all features",
							"originalRequest": {
								"method": "GET",
								"header": [],
								"url": {
									"raw": "http://localhost:3000/api/feature/",
									"protocol": "http",
									"host": [
										"localhost"
									],
									"port": "3000",
									"path": [
										"api",
										"feature",
										""
									]
								}
							},
							"status": "OK",
							"code": 200,
							"_postman_previewlanguage": "json",
							"header": [
								{
									"key": "X-Powered-By",
									"value": "Express"
								},
								{
									"key": "Content-Type",
									"value": "application/json; charset=utf-8"
								},
								{
									"key": "Content-Length",
									"value": "480"
								},
								{
									"key": "ETag",
									"value": "W/\"1e0-w/SEoTckJOzDEb+naCLduDq9LNA\""
								},
								{
									"key": "Date",
									"value": "Thu, 14 Jan 2021 13:52:51 GMT"
								},
								{
									"key": "Connection",
									"value": "keep-alive"
								}
							],
							"cookie": [],
							"body": "[\n    {\n        \"featureId\": 1,\n        \"name\": \"Kapacitet\",\n        \"categoryId\": 5,\n        \"category\": {\n            \"categoryId\": 5,\n            \"name\": \"Hard diskovi\",\n            \"imagePath\": \"assets/pc/memory/hard.jpg\",\n            \"parentCategoryId\": 4\n        }\n    },\n    {\n        \"featureId\": 3,\n        \"name\": \"Tehnologija\",\n        \"categoryId\": 5,\n        \"category\": {\n            \"categoryId\": 5,\n            \"name\": \"Hard diskovi\",\n            \"imagePath\": \"assets/pc/memory/hard.jpg\",\n            \"parentCategoryId\": 4\n        }\n    },\n    {\n        \"featureId\": 2,\n        \"name\": \"Tip\",\n        \"categoryId\": 5,\n        \"category\": {\n            \"categoryId\": 5,\n            \"name\": \"Hard diskovi\",\n            \"imagePath\": \"assets/pc/memory/hard.jpg\",\n            \"parentCategoryId\": 4\n        }\n    }\n]"
						}
					]
				},
				{
					"name": "Get a single feature",
					"request": {
						"method": "GET",
						"header": [],
						"url": {
							"raw": "http://localhost:3000/api/feature/1/",
							"protocol": "http",
							"host": [
								"localhost"
							],
							"port": "3000",
							"path": [
								"api",
								"feature",
								"1",
								""
							]
						}
					},
					"response": [
						{
							"name": "Get all features",
							"originalRequest": {
								"method": "GET",
								"header": [],
								"url": {
									"raw": "http://localhost:3000/api/feature/",
									"protocol": "http",
									"host": [
										"localhost"
									],
									"port": "3000",
									"path": [
										"api",
										"feature",
										""
									]
								}
							},
							"status": "OK",
							"code": 200,
							"_postman_previewlanguage": "json",
							"header": [
								{
									"key": "X-Powered-By",
									"value": "Express"
								},
								{
									"key": "Content-Type",
									"value": "application/json; charset=utf-8"
								},
								{
									"key": "Content-Length",
									"value": "480"
								},
								{
									"key": "ETag",
									"value": "W/\"1e0-w/SEoTckJOzDEb+naCLduDq9LNA\""
								},
								{
									"key": "Date",
									"value": "Thu, 14 Jan 2021 13:52:51 GMT"
								},
								{
									"key": "Connection",
									"value": "keep-alive"
								}
							],
							"cookie": [],
							"body": "[\n    {\n        \"featureId\": 1,\n        \"name\": \"Kapacitet\",\n        \"categoryId\": 5,\n        \"category\": {\n            \"categoryId\": 5,\n            \"name\": \"Hard diskovi\",\n            \"imagePath\": \"assets/pc/memory/hard.jpg\",\n            \"parentCategoryId\": 4\n        }\n    },\n    {\n        \"featureId\": 3,\n        \"name\": \"Tehnologija\",\n        \"categoryId\": 5,\n        \"category\": {\n            \"categoryId\": 5,\n            \"name\": \"Hard diskovi\",\n            \"imagePath\": \"assets/pc/memory/hard.jpg\",\n            \"parentCategoryId\": 4\n        }\n    },\n    {\n        \"featureId\": 2,\n        \"name\": \"Tip\",\n        \"categoryId\": 5,\n        \"category\": {\n            \"categoryId\": 5,\n            \"name\": \"Hard diskovi\",\n            \"imagePath\": \"assets/pc/memory/hard.jpg\",\n            \"parentCategoryId\": 4\n        }\n    }\n]"
						},
						{
							"name": "Get a single feature",
							"originalRequest": {
								"method": "GET",
								"header": [],
								"url": {
									"raw": "http://localhost:3000/api/feature/1/",
									"protocol": "http",
									"host": [
										"localhost"
									],
									"port": "3000",
									"path": [
										"api",
										"feature",
										"1",
										""
									]
								}
							},
							"status": "OK",
							"code": 200,
							"_postman_previewlanguage": "json",
							"header": [
								{
									"key": "X-Powered-By",
									"value": "Express"
								},
								{
									"key": "Content-Type",
									"value": "application/json; charset=utf-8"
								},
								{
									"key": "Content-Length",
									"value": "160"
								},
								{
									"key": "ETag",
									"value": "W/\"a0-IPu54GA/iC1NwGaqnyuaCBQ9zPI\""
								},
								{
									"key": "Date",
									"value": "Thu, 14 Jan 2021 14:25:13 GMT"
								},
								{
									"key": "Connection",
									"value": "keep-alive"
								}
							],
							"cookie": [],
							"body": "{\n    \"featureId\": 1,\n    \"name\": \"Kapacitet\",\n    \"categoryId\": 5,\n    \"category\": {\n        \"categoryId\": 5,\n        \"name\": \"Hard diskovi\",\n        \"imagePath\": \"assets/pc/memory/hard.jpg\",\n        \"parentCategoryId\": 4\n    }\n}"
						}
					]
				},
				{
					"name": "Add a new feature",
					"request": {
						"method": "POST",
						"header": [],
						"body": {
							"mode": "raw",
							"raw": "{\n    \"name\": \"Snaga\",\n    \"categoryId\": 2\n}",
							"options": {
								"raw": {
									"language": "json"
								}
							}
						},
						"url": {
							"raw": "http://localhost:3000/api/feature/",
							"protocol": "http",
							"host": [
								"localhost"
							],
							"port": "3000",
							"path": [
								"api",
								"feature",
								""
							]
						}
					},
					"response": [
						{
							"name": "Add a new feature",
							"originalRequest": {
								"method": "POST",
								"header": [],
								"body": {
									"mode": "raw",
									"raw": "{\n    \"name\": \"Snaga\",\n    \"categoryId\": 2\n}",
									"options": {
										"raw": {
											"language": "json"
										}
									}
								},
								"url": {
									"raw": "http://localhost:3000/api/feature/",
									"protocol": "http",
									"host": [
										"localhost"
									],
									"port": "3000",
									"path": [
										"api",
										"feature",
										""
									]
								}
							},
							"status": "Created",
							"code": 201,
							"_postman_previewlanguage": "json",
							"header": [
								{
									"key": "X-Powered-By",
									"value": "Express"
								},
								{
									"key": "Content-Type",
									"value": "application/json; charset=utf-8"
								},
								{
									"key": "Content-Length",
									"value": "154"
								},
								{
									"key": "ETag",
									"value": "W/\"9a-QE7Usp2NaDnFfixBNLhVHyGByOw\""
								},
								{
									"key": "Date",
									"value": "Thu, 14 Jan 2021 14:35:19 GMT"
								},
								{
									"key": "Connection",
									"value": "keep-alive"
								}
							],
							"cookie": [],
							"body": "{\n    \"featureId\": 5,\n    \"name\": \"Snaga\",\n    \"categoryId\": 2,\n    \"category\": {\n        \"categoryId\": 2,\n        \"name\": \"Kucna elektronika\",\n        \"imagePath\": \"assets/home.jpg\",\n        \"parentCategoryId\": null\n    }\n}"
						}
					]
				},
				{
					"name": "Edit a single feature",
					"request": {
						"method": "PATCH",
						"header": [],
						"body": {
							"mode": "raw",
							"raw": "{\n    \"name\": \"Napon\"\n}",
							"options": {
								"raw": {
									"language": "json"
								}
							}
						},
						"url": {
							"raw": "http://localhost:3000/api/feature/4",
							"protocol": "http",
							"host": [
								"localhost"
							],
							"port": "3000",
							"path": [
								"api",
								"feature",
								"4"
							]
						}
					},
					"response": [
						{
							"name": "Edit a single feature",
							"originalRequest": {
								"method": "PATCH",
								"header": [],
								"body": {
									"mode": "raw",
									"raw": "{\n    \"name\": \"Napon\"\n}",
									"options": {
										"raw": {
											"language": "json"
										}
									}
								},
								"url": {
									"raw": "http://localhost:3000/api/feature/4",
									"protocol": "http",
									"host": [
										"localhost"
									],
									"port": "3000",
									"path": [
										"api",
										"feature",
										"4"
									]
								}
							},
							"status": "OK",
							"code": 200,
							"_postman_previewlanguage": "json",
							"header": [
								{
									"key": "X-Powered-By",
									"value": "Express"
								},
								{
									"key": "Content-Type",
									"value": "application/json; charset=utf-8"
								},
								{
									"key": "Content-Length",
									"value": "154"
								},
								{
									"key": "ETag",
									"value": "W/\"9a-+uH7LVo1Qm3Ht9TgnaCdjsyWG5g\""
								},
								{
									"key": "Date",
									"value": "Thu, 14 Jan 2021 14:38:32 GMT"
								},
								{
									"key": "Connection",
									"value": "keep-alive"
								}
							],
							"cookie": [],
							"body": "{\n    \"featureId\": 4,\n    \"name\": \"Napon\",\n    \"categoryId\": 2,\n    \"category\": {\n        \"categoryId\": 2,\n        \"name\": \"Kucna elektronika\",\n        \"imagePath\": \"assets/home.jpg\",\n        \"parentCategoryId\": null\n    }\n}"
						}
					]
				}
			],
			"event": [
				{
					"listen": "prerequest",
					"script": {
						"type": "text/javascript",
						"exec": [
							""
						]
					}
				},
				{
					"listen": "test",
					"script": {
						"type": "text/javascript",
						"exec": [
							""
						]
					}
				}
			]
		}
	],
	"auth": {
		"type": "bearer",
		"bearer": [
			{
				"key": "token",
				"value": "eyJhbGciOiJIUzI1NiIsInR5cCI6IkpXVCJ9.eyJyb2xlIjoiYWRtaW5pc3RyYXRvciIsImFkbWluaXN0cmF0b3JJZCI6NCwiaWRlbnRpdHkiOiJhZG1pbiIsImV4cCI6MTYxMTkyMzMyNi40NTksImlwIjoiOjoxIiwidWEiOiJQb3N0bWFuUnVudGltZS83LjI2LjgiLCJpYXQiOjE2MTA3MTM3MjZ9.jwLWI3l_3o1LcPkJsxUPml8-n_HV94JJtDxJBAFRjAI",
				"type": "string"
			}
		]
	},
	"event": [
		{
			"listen": "prerequest",
			"script": {
				"type": "text/javascript",
				"exec": [
					""
				]
			}
		},
		{
			"listen": "test",
			"script": {
				"type": "text/javascript",
				"exec": [
					""
				]
			}
		}
	]
}